LICENSE
MANIFEST.in
README.rst
setup.py
covador/__init__.py
covador/aiohttp.py
covador/aiohttp_t.py
covador/ast_transformer.py
covador/autils.py
covador/compat.py
covador/django.py
covador/errors.py
covador/flask.py
covador/gen_validator_t.py
covador/merge_getter_t.py
covador/sanic.py
covador/tornado.py
covador/types.py
covador/utils.py
covador/vdecorator.py
covador.egg-info/PKG-INFO
covador.egg-info/SOURCES.txt
covador.egg-info/dependency_links.txt
covador.egg-info/not-zip-safe
covador.egg-info/top_level.txt